<?xml version='1.0' encoding='UTF-8'?><soapenv:Envelope xmlns:soapenv="http://www.w3.org/2003/05/soap-envelope"><soapenv:Body><ns1:queryResponse xmlns:ns1="http://api.zuora.com/"><ns1:result><ns1:done>true</ns1:done><ns1:queryLocator xmlns:xsi="http://www.w3.org/2001/XMLSchema-instance" xsi:nil="1" /><ns1:records xmlns:ns2="http://object.api.zuora.com/" xmlns:xsi="http://www.w3.org/2001/XMLSchema-instance" xsi:type="ns2:Account"><ns2:Id>4028e488348752ce0134876a25867cb2</ns2:Id><ns2:AccountNumber>test-1</ns2:AccountNumber><ns2:AutoPay>false</ns2:AutoPay><ns2:Balance>0</ns2:Balance><ns2:Batch>Batch1</ns2:Batch><ns2:BillCycleDay>1</ns2:BillCycleDay><ns2:CreatedDate>2011-12-28T17:23:27.000-08:00</ns2:CreatedDate><ns2:CreditBalance>0</ns2:CreditBalance><ns2:Currency>USD</ns2:Currency><ns2:Name>FooBar</ns2:Name><ns2:PaymentTerm>Due Upon Receipt</ns2:PaymentTerm><ns2:Status>Draft</ns2:Status><ns2:TotalInvoiceBalance>0</ns2:TotalInvoiceBalance><ns2:UpdatedDate>2011-12-28T17:23:27.000-08:00</ns2:UpdatedDate></ns1:records><ns1:records xmlns:ns2="http://object.api.zuora.com/" xmlns:xsi="http://www.w3.org/2001/XMLSchema-instance" xsi:type="ns2:Account"><ns2:Id>4028e4883491c509013492cd13e2455f</ns2:Id><ns2:AccountNumber>testmebabe</ns2:AccountNumber><ns2:AutoPay>false</ns2:AutoPay><ns2:Balance>0</ns2:Balance><ns2:Batch>Batch1</ns2:Batch><ns2:BillCycleDay>1</ns2:BillCycleDay><ns2:CreatedDate>2011-12-30T22:27:20.000-08:00</ns2:CreatedDate><ns2:CreditBalance>0</ns2:CreditBalance><ns2:Currency>USD</ns2:Currency><ns2:Name>Example</ns2:Name><ns2:PaymentTerm>Due Upon Receipt</ns2:PaymentTerm><ns2:Status>Draft</ns2:Status><ns2:TotalInvoiceBalance>0</ns2:TotalInvoiceBalance><ns2:UpdatedDate>2011-12-30T22:27:20.000-08:00</ns2:UpdatedDate></ns1:records><ns1:size>2</ns1:size></ns1:result></ns1:queryResponse></soapenv:Body></soapenv:Envelope>
