<?xml version='1.0' encoding='UTF-8'?><soapenv:Envelope xmlns:soapenv="http://www.w3.org/2003/05/soap-envelope"><soapenv:Body><ns1:queryResponse xmlns:ns1="http://api.zuora.com/"><ns1:result><ns1:done>true</ns1:done><ns1:queryLocator xmlns:xsi="http://www.w3.org/2001/XMLSchema-instance" xsi:nil="1" /><ns1:records xmlns:ns2="http://object.api.zuora.com/" xmlns:xsi="http://www.w3.org/2001/XMLSchema-instance" xsi:type="ns2:Contact"><ns2:Id>4028e4873491cc77013495dff7656a4f</ns2:Id><ns2:AccountId>4028e488348752ce0134876a25867cb2</ns2:AccountId><ns2:FirstName>Joe</ns2:FirstName><ns2:LastName>Testing</ns2:LastName></ns1:records><ns1:size>1</ns1:size></ns1:result></ns1:queryResponse></soapenv:Body></soapenv:Envelope>
